sanic_route/__init__.py
sanic_route/router.py
sanic_route-0.0.1.dist-info/METADATA
sanic_route-0.0.1.dist-info/WHEEL
sanic_route-0.0.1.dist-info/license
sanic_route-0.0.1.dist-info/top_level.txt
sanic_route-0.0.1.dist-info/RECORD
