Metadata-Version: 2.1
Name: sanic-route
Version: 0.0.1
Summary: yet a sanic route extension.
Home-page: https://github.com/chenshenchao/sanic_route
Author: chenshenchao
Author-email: chenshenchao@outlook.com
License: MIT
Keywords: sanic route
Platform: any
Classifier: License :: OSI Approved :: MIT License
Classifier: Intended Audience :: Developers
Classifier: Operating System :: OS Independent
Classifier: Programming Language :: Python :: 3
Classifier: Programming Language :: Python :: 3.7
Classifier: Programming Language :: Python :: 3.8
Classifier: Programming Language :: Python :: 3.9
Classifier: Programming Language :: Python :: 3.10
License-File: license
Requires-Dist: sanic (==22.9.0)
